{
  "games": 40,
  "nn_wins": 17,
  "heuristic_wins": 23,
  "ties": 0,
  "nn_mean_score": 32.275,
  "heuristic_mean_score": 31.55,
  "nn_mean_margin": 0.725,
  "nn_win_rate": 0.425,
  "nn_rate_ge_100": 0.0,
  "nn_rate_ge_120": 0.0,
  "nn_win_rate_ci95": [
    0.2851,
    0.5781
  ],
  "stage1": {
    "games": 20,
    "nn_wins": 10,
    "heuristic_wins": 10,
    "ties": 0,
    "nn_mean_score": 29.55,
    "heuristic_mean_score": 29.95,
    "nn_mean_margin": -0.4,
    "nn_win_rate": 0.5,
    "nn_rate_ge_100": 0.0,
    "nn_rate_ge_120": 0.0
  },
  "stage1_continue_threshold": 0.5,
  "stage2_enabled": true,
  "stage2": {
    "games": 20,
    "nn_wins": 7,
    "heuristic_wins": 13,
    "ties": 0,
    "nn_mean_score": 35.0,
    "heuristic_mean_score": 33.15,
    "nn_mean_margin": 1.85,
    "nn_win_rate": 0.35,
    "nn_rate_ge_100": 0.0,
    "nn_rate_ge_120": 0.0
  },
  "promoted": false,
  "min_promotion_win_rate": 0.5,
  "gate_value_blend": 0.8,
  "gate_mcts_sims": 40
}